odmcp/__init__.py
odmcp/cli.py
odmcp/client.py
odmcp/utils.py
odmcp/providers/__template__.py
odmcp/providers/ch_sbb.py
odmcp_fastmcp-0.1.28.dist-info/METADATA
odmcp_fastmcp-0.1.28.dist-info/WHEEL
odmcp_fastmcp-0.1.28.dist-info/entry_points.txt
odmcp_fastmcp-0.1.28.dist-info/licenses/LICENSE
odmcp_fastmcp-0.1.28.dist-info/RECORD
