Metadata-Version: 2.4
Name: odmcp-fastmcp
Version: 0.1.28
Summary: Python MCP servers exposing Open Data to compatible LLM clients.
Project-URL: Homepage, https://github.com/fastmcp-me/opendatamcp#readme
Project-URL: Repository, https://github.com/fastmcp-me/opendatamcp.git
Project-URL: Issues, https://github.com/fastmcp-me/opendatamcp/issues
License-File: LICENSE
Requires-Python: >=3.10
Requires-Dist: httpx>=0.28.0
Requires-Dist: mcp>=1.0.0
